synology_abfb_log_parser/__about__.py
synology_abfb_log_parser/__init__.py
synology_abfb_log_parser/abfb_log_parser.py
synology_abfb_log_parser-0.3.0.dist-info/METADATA
synology_abfb_log_parser-0.3.0.dist-info/WHEEL
synology_abfb_log_parser-0.3.0.dist-info/licenses/LICENSE.md
synology_abfb_log_parser-0.3.0.dist-info/RECORD
