Metadata-Version: 2.3
Name: synology_abfb_log_parser
Version: 0.3.0
Summary: Synology Active Backup for Business log parser
Project-URL: Homepage, https://github.com/NiceGuyIT/synology_abfb_log_parser
Project-URL: Repository, https://github.com/NiceGuyIT/synology_abfb_log_parser
Project-URL: Documentation, https://github.com/NiceGuyIT/synology_abfb_log_parser
Project-URL: Bug Tracker, https://github.com/NiceGuyIT/synology_abfb_log_parser/issues
Author-email: David Randall <David@NiceGuyIT.biz>
License: Copyright (c) 2022 Nice Guy IT, LLC
License-File: LICENSE.md
Classifier: License :: OSI Approved :: MIT License
Classifier: Operating System :: OS Independent
Classifier: Programming Language :: Python :: 3
Requires-Python: >=3.6
